{
  "model_type": "iv_gmm",
  "model_label": "IV-GMM",
  "asset": {
    "id": "59d06eb6-c01f-4ee6-85c9-6b572bbd5ff4",
    "kind": "dataset_csv",
    "title": "upgrade_panel.csv",
    "filename": "upgrade_panel.csv",
    "description": "upgrade_panel.csv",
    "content_type": "text/csv",
    "source_url": "",
    "metadata": {
      "size_bytes": 289095,
      "original_filename": "upgrade_panel.csv",
      "storage_backend": "local"
    },
    "created_at": "2026-04-02T02:57:26.995002",
    "updated_at": "2026-04-02T02:57:27.013674"
  },
  "dependent": "outcome_y",
  "regressors": [
    "const",
    "size",
    "leverage",
    "post",
    "endogenous_x"
  ],
  "observations": 648,
  "r_squared": 0.6238163607047971,
  "adj_r_squared": 0.6214761825443293,
  "pseudo_r_squared": null,
  "aic": null,
  "bic": null,
  "log_likelihood": null,
  "coefficients": [
    {
      "term": "const",
      "coefficient": 3.520472205336905,
      "std_error": 0.7185304797314824,
      "t_stat": 4.89954470219902,
      "p_value": 9.605899391473827e-07
    },
    {
      "term": "size",
      "coefficient": 0.5914182921177928,
      "std_error": 0.060548623680332606,
      "t_stat": 9.76765872070346,
      "p_value": 0.0
    },
    {
      "term": "leverage",
      "coefficient": -1.1619510117188152,
      "std_error": 1.2697703413272448,
      "t_stat": -0.9150875350453296,
      "p_value": 0.3601456782208401
    },
    {
      "term": "post",
      "coefficient": 2.1233886671195847,
      "std_error": 0.09244492400416701,
      "t_stat": 22.969229408678746,
      "p_value": 0.0
    },
    {
      "term": "endogenous_x",
      "coefficient": 0.5065604567690617,
      "std_error": 0.06380801324678985,
      "t_stat": 7.938821959709684,
      "p_value": 1.9984014443252818e-15
    }
  ],
  "narrative": [
    "IV-GMM estimated with linearmodels on upgrade_panel.csv.",
    "Endogenous regressor: endogenous_x.",
    "Instruments: instrument_z."
  ],
  "sample_columns": [
    "outcome_y",
    "size",
    "leverage",
    "post",
    "endogenous_x",
    "instrument_z"
  ],
  "sample_preview": [
    {
      "outcome_y": 8.281342947667275,
      "size": 8.519775911467494,
      "leverage": 0.3577590135791016,
      "post": 0,
      "endogenous_x": 0.2785972991161518,
      "instrument_z": -0.1435168424451554
    },
    {
      "outcome_y": 7.161166663415577,
      "size": 7.55721041465215,
      "leverage": 0.3378183221465689,
      "post": 0,
      "endogenous_x": 1.1977342200420291,
      "instrument_z": 1.4316570462193818
    },
    {
      "outcome_y": 7.582391886802917,
      "size": 7.823590785770317,
      "leverage": 0.3343232278441892,
      "post": 0,
      "endogenous_x": 0.2791971515539841,
      "instrument_z": 1.0577328335812757
    },
    {
      "outcome_y": 8.19643779930995,
      "size": 8.058331858128255,
      "leverage": 0.3581110765958445,
      "post": 0,
      "endogenous_x": 1.693126004491981,
      "instrument_z": 1.2478999752354007
    },
    {
      "outcome_y": 6.775339604671813,
      "size": 7.790582349444769,
      "leverage": 0.3323010132904619,
      "post": 0,
      "endogenous_x": -0.6336680485148168,
      "instrument_z": -0.7576141862667286
    }
  ],
  "specification": {
    "asset_id": "59d06eb6-c01f-4ee6-85c9-6b572bbd5ff4",
    "model_family": "econometrics_baseline",
    "model_type": "iv_gmm",
    "dependent": "outcome_y",
    "independents": [
      "size"
    ],
    "controls": [
      "leverage",
      "post"
    ],
    "endogenous_column": "endogenous_x",
    "instrument_columns": [
      "instrument_z"
    ],
    "engine": "linearmodels",
    "variant_label": "gmm_post"
  },
  "audit_trail": {
    "sample_asset_id": "59d06eb6-c01f-4ee6-85c9-6b572bbd5ff4",
    "sample_title": "upgrade_panel.csv",
    "sample_download_url": "/api/assets/59d06eb6-c01f-4ee6-85c9-6b572bbd5ff4/download",
    "rows_used": 648,
    "sample_columns": [
      "outcome_y",
      "size",
      "leverage",
      "post",
      "endogenous_x",
      "instrument_z"
    ],
    "covariance_type": "robust",
    "manual_checklist": [
      "Download the prepared sample asset referenced in sample_asset_id.",
      "Rebuild any derived regressors listed in derived_columns before estimation.",
      "Use the listed regressors, covariance_type, and sample filters to reproduce the model manually.",
      "Compare the reproduced coefficient table with the coefficients array term by term."
    ],
    "engine": "linearmodels",
    "derived_columns": [],
    "filters": [
      "Rows with missing variables are dropped."
    ]
  },
  "engine": "linearmodels",
  "primary_tables": [
    "first_stage_diagnostics",
    "over_identification_diagnostics"
  ],
  "robustness_tables": [
    "weighting_matrix_summary"
  ],
  "tables": {
    "first_stage_diagnostics": [
      {
        "index": "endogenous_x",
        "rsquared": 0.77396402566144,
        "partial.rsquared": 0.7721217444928744,
        "shea.rsquared": 0.7721217444928737,
        "f.stat": 2040.0543354750835,
        "f.pval": 0.0,
        "f.dist": "chi2(1)"
      }
    ],
    "over_identification_diagnostics": [
      {
        "j_stat": 1.8282582931055014e-23,
        "pvalue": null,
        "nobs": 648.0
      }
    ],
    "weighting_matrix_summary": [
      {
        "weight_type": "robust",
        "cov_type": "robust",
        "iterations": 2.0
      }
    ]
  },
  "figures": [
    {
      "asset_id": "cfd41e7e-874f-4f22-a4d3-b5f409499b31",
      "title": "IV-GMM First-stage Fit",
      "summary": "Observed endogenous regressor versus first-stage fitted values.",
      "download_url": "/api/assets/cfd41e7e-874f-4f22-a4d3-b5f409499b31/download",
      "asset": {
        "id": "cfd41e7e-874f-4f22-a4d3-b5f409499b31",
        "kind": "chart_png",
        "title": "upgrade_panel-iv_gmm_first_stage_fit.png",
        "filename": "upgrade_panel-iv_gmm_first_stage_fit.png",
        "description": "Observed endogenous regressor versus first-stage fitted values.",
        "content_type": "image/png",
        "source_url": "",
        "metadata": {
          "size_bytes": 136190,
          "original_filename": "upgrade_panel-iv_gmm_first_stage_fit.png",
          "storage_backend": "local",
          "analysis_kind": "model_figure",
          "source_model": "IV-GMM First-stage Fit",
          "source_asset_id": "59d06eb6-c01f-4ee6-85c9-6b572bbd5ff4",
          "summary": "Observed endogenous regressor versus first-stage fitted values."
        },
        "created_at": "2026-04-02T02:57:38.428208+00:00",
        "updated_at": "2026-04-02T02:57:38.442495+00:00"
      }
    }
  ],
  "metrics": {},
  "paper_output_contract": {
    "primary_tables": [
      "first_stage_diagnostics",
      "over_identification_diagnostics"
    ],
    "robustness_tables": [
      "weighting_matrix_summary"
    ],
    "figure_count": 1
  },
  "workflow_type": "model",
  "model_family": "econometrics_baseline",
  "interpretation": {
    "headline": "IV-GMM estimates are exposed in full so you can read the result and reproduce it manually.",
    "sections": [
      {
        "title": "What is shown on this page",
        "items": [
          "Coefficient table is shown with standard errors, test statistics, p-values, and significance stars.",
          "Supporting tables included: first_stage_diagnostics, over_identification_diagnostics, weighting_matrix_summary.",
          "Figures included: IV-GMM First-stage Fit."
        ]
      },
      {
        "title": "How to read the main result",
        "items": [
          "Use the metrics panel for headline diagnostics, then move to the coefficient table or supporting tables for the formal result.",
          "The specification block records the exact equation or parameterization that should be reproduced manually."
        ]
      },
      {
        "title": "Manual replication focus",
        "items": [
          "Download the referenced sample and rebuild all listed derived columns before estimation.",
          "Match the equation, regressors, covariance type, and sample filters exactly.",
          "Compare the resulting table or figure object term by term with the result shown here."
        ]
      }
    ],
    "paper_outputs": [
      "first_stage_diagnostics",
      "over_identification_diagnostics",
      "weighting_matrix_summary",
      "IV-GMM First-stage Fit"
    ]
  },
  "template_id": "",
  "template_name": "",
  "variant_label": "gmm_post",
  "variant_spec": {},
  "result_record_id": "d37c88eb-1021-449c-ae7e-4c96e3d52441",
  "result_detail_path": "/data-lab/results/models/d37c88eb-1021-449c-ae7e-4c96e3d52441"
}