{
  "workflow_type": "data_processing",
  "processing_family": "cleaning_transforms",
  "template_id": "",
  "template_name": "",
  "variant_label": "minmax_variant",
  "variant_spec": {
    "impute_method": "mean",
    "minmax_scale_columns": [
      "size",
      "leverage"
    ],
    "outlier_threshold": 1.25
  },
  "effective_specification": {
    "asset_id": "742a2af5-b7f8-4b12-8914-a535cd9ee440",
    "workflow_group": "cleaning_transforms",
    "impute_columns": [
      "size",
      "leverage"
    ],
    "winsorize_columns": [
      "outcome_y"
    ],
    "winsor_lower_quantile": 0.01,
    "winsor_upper_quantile": 0.99,
    "outlier_columns": [
      "outcome_y"
    ],
    "outlier_method": "iqr",
    "impute_method": "mean",
    "minmax_scale_columns": [
      "size",
      "leverage"
    ],
    "outlier_threshold": 1.25
  },
  "asset": {
    "id": "7a79d0d2-3da8-4460-9c51-2f180f2828e7",
    "kind": "dataset_csv",
    "title": "panel_dataset-prepared.csv",
    "filename": "panel_dataset-prepared.csv",
    "description": "Prepared analysis sample derived from panel_dataset.csv",
    "content_type": "text/csv",
    "source_url": "",
    "metadata": {
      "size_bytes": 287930,
      "original_filename": "panel_dataset-prepared.csv",
      "storage_backend": "local",
      "preparation_summary": {
        "rows_initial": 648,
        "rows_after_prepare": 648,
        "rows_removed_for_missing_required": 0,
        "duplicate_rows_removed": 0,
        "columns": [
          "firm_id",
          "date",
          "calendar_year",
          "month_index",
          "treated",
          "post",
          "staggered_post",
          "event_time",
          "staggered_event_time",
          "treatment_time",
          "unit",
          "size",
          "leverage",
          "instrument_z",
          "endogenous_x",
          "outcome_y",
          "binary_outcome",
          "count_outcome",
          "multiclass_outcome",
          "secondary_outcome",
          "running_score",
          "export_flow",
          "origin_gdp",
          "destination_gdp",
          "distance_km",
          "working_capital",
          "retained_earnings",
          "ebit",
          "market_equity",
          "sales",
          "total_assets",
          "total_liabilities",
          "net_income",
          "revenue",
          "equity"
        ],
        "required_columns": [],
        "numeric_columns": [],
        "binary_columns": [],
        "date_columns": [],
        "imputed_columns": {
          "size": "mean",
          "leverage": "mean"
        },
        "winsorized_columns": {
          "outcome_y": {
            "lower": 0.01,
            "upper": 0.99
          }
        },
        "transformed_columns": {
          "log": [],
          "zscore": [],
          "minmax": [
            "size",
            "leverage"
          ]
        },
        "time_series_features": {
          "sort_column": "",
          "group_column": "",
          "difference_columns": [],
          "return_columns": [],
          "lag_columns": [],
          "lead_columns": [],
          "rolling_mean_columns": [],
          "rolling_volatility_columns": []
        },
        "derived_columns": [],
        "outlier_columns": [
          "outcome_y"
        ],
        "outlier_method": "iqr",
        "outlier_threshold": 1.25,
        "outliers_removed": 0,
        "missing_by_column": {
          "firm_id": 0,
          "date": 0,
          "calendar_year": 0,
          "month_index": 0,
          "treated": 0,
          "post": 0,
          "staggered_post": 0,
          "event_time": 0,
          "staggered_event_time": 324,
          "treatment_time": 324,
          "unit": 0,
          "size": 0,
          "leverage": 0,
          "instrument_z": 0,
          "endogenous_x": 0,
          "outcome_y": 0,
          "binary_outcome": 0,
          "count_outcome": 0,
          "multiclass_outcome": 0,
          "secondary_outcome": 0,
          "running_score": 0,
          "export_flow": 0,
          "origin_gdp": 0,
          "destination_gdp": 0,
          "distance_km": 0,
          "working_capital": 0,
          "retained_earnings": 0,
          "ebit": 0,
          "market_equity": 0,
          "sales": 0,
          "total_assets": 0,
          "total_liabilities": 0,
          "net_income": 0,
          "revenue": 0,
          "equity": 0
        }
      },
      "source_asset_id": "742a2af5-b7f8-4b12-8914-a535cd9ee440"
    },
    "created_at": "2026-04-02T03:16:15.548557",
    "updated_at": "2026-04-02T03:16:15.558016"
  },
  "summary": {
    "rows_initial": 648,
    "rows_after_prepare": 648,
    "rows_removed_for_missing_required": 0,
    "duplicate_rows_removed": 0,
    "columns": [
      "firm_id",
      "date",
      "calendar_year",
      "month_index",
      "treated",
      "post",
      "staggered_post",
      "event_time",
      "staggered_event_time",
      "treatment_time",
      "unit",
      "size",
      "leverage",
      "instrument_z",
      "endogenous_x",
      "outcome_y",
      "binary_outcome",
      "count_outcome",
      "multiclass_outcome",
      "secondary_outcome",
      "running_score",
      "export_flow",
      "origin_gdp",
      "destination_gdp",
      "distance_km",
      "working_capital",
      "retained_earnings",
      "ebit",
      "market_equity",
      "sales",
      "total_assets",
      "total_liabilities",
      "net_income",
      "revenue",
      "equity"
    ],
    "required_columns": [],
    "numeric_columns": [],
    "binary_columns": [],
    "date_columns": [],
    "imputed_columns": {
      "size": "mean",
      "leverage": "mean"
    },
    "winsorized_columns": {
      "outcome_y": {
        "lower": 0.01,
        "upper": 0.99
      }
    },
    "transformed_columns": {
      "log": [],
      "zscore": [],
      "minmax": [
        "size",
        "leverage"
      ]
    },
    "time_series_features": {
      "sort_column": "",
      "group_column": "",
      "difference_columns": [],
      "return_columns": [],
      "lag_columns": [],
      "lead_columns": [],
      "rolling_mean_columns": [],
      "rolling_volatility_columns": []
    },
    "derived_columns": [],
    "outlier_columns": [
      "outcome_y"
    ],
    "outlier_method": "iqr",
    "outlier_threshold": 1.25,
    "outliers_removed": 0,
    "missing_by_column": {
      "firm_id": 0,
      "date": 0,
      "calendar_year": 0,
      "month_index": 0,
      "treated": 0,
      "post": 0,
      "staggered_post": 0,
      "event_time": 0,
      "staggered_event_time": 324,
      "treatment_time": 324,
      "unit": 0,
      "size": 0,
      "leverage": 0,
      "instrument_z": 0,
      "endogenous_x": 0,
      "outcome_y": 0,
      "binary_outcome": 0,
      "count_outcome": 0,
      "multiclass_outcome": 0,
      "secondary_outcome": 0,
      "running_score": 0,
      "export_flow": 0,
      "origin_gdp": 0,
      "destination_gdp": 0,
      "distance_km": 0,
      "working_capital": 0,
      "retained_earnings": 0,
      "ebit": 0,
      "market_equity": 0,
      "sales": 0,
      "total_assets": 0,
      "total_liabilities": 0,
      "net_income": 0,
      "revenue": 0,
      "equity": 0
    }
  },
  "preview_rows": [
    {
      "firm_id": "firm_01",
      "date": "2018-01-31",
      "calendar_year": 2018,
      "month_index": 1,
      "treated": 1,
      "post": 0,
      "staggered_post": 0,
      "event_time": -18,
      "staggered_event_time": -18.0,
      "treatment_time": 18.0,
      "unit": "firm_01",
      "size": 0.2657518825675091,
      "leverage": 0.46290562879832237,
      "instrument_z": -0.1435168424451554,
      "endogenous_x": 0.2785972991161518,
      "outcome_y": 8.281342947667275,
      "binary_outcome": 0,
      "count_outcome": 1,
      "multiclass_outcome": 0,
      "secondary_outcome": 8.061791269331776,
      "running_score": 0.7698387038457276,
      "export_flow": 49.40883917797032,
      "origin_gdp": 6707.077236995387,
      "destination_gdp": 5124.128155689759,
      "distance_km": 506.1984144232085,
      "working_capital": 61057.22892506472,
      "retained_earnings": 41137.34917451515,
      "ebit": 33273.31812219427,
      "market_equity": 335260.0152858213,
      "sales": 383648.0257341592,
      "total_assets": 501293.02907292894,
      "total_liabilities": 213372.0724041828,
      "net_income": 26375.54605689663,
      "revenue": 383648.0257341592,
      "equity": 287920.9566687462
    },
    {
      "firm_id": "firm_01",
      "date": "2018-02-28",
      "calendar_year": 2018,
      "month_index": 2,
      "treated": 1,
      "post": 0,
      "staggered_post": 0,
      "event_time": -17,
      "staggered_event_time": -17.0,
      "treatment_time": 18.0,
      "unit": "firm_01",
      "size": 0.0,
      "leverage": 0.3682188743444447,
      "instrument_z": 1.4316570462193818,
      "endogenous_x": 1.1977342200420291,
      "outcome_y": 7.161166663415577,
      "binary_outcome": 1,
      "count_outcome": 3,
      "multiclass_outcome": 1,
      "secondary_outcome": 7.318611368946235,
      "running_score": -1.2578541177844715,
      "export_flow": 91.97699374857942,
      "origin_gdp": 6549.205151959514,
      "destination_gdp": 4695.745866446325,
      "distance_km": 499.9748647163789,
      "working_capital": 25865.74300359386,
      "retained_earnings": 15937.67861929455,
      "ebit": 12858.699383533743,
      "market_equity": 124948.65584723122,
      "sales": 143429.89314427826,
      "total_assets": 191449.74034320377,
      "total_liabilities": 84857.58709080162,
      "net_income": 15525.445856681252,
      "revenue": 143429.89314427826,
      "equity": 106592.15325240216
    },
    {
      "firm_id": "firm_01",
      "date": "2018-03-31",
      "calendar_year": 2018,
      "month_index": 3,
      "treated": 1,
      "post": 0,
      "staggered_post": 0,
      "event_time": -16,
      "staggered_event_time": -16.0,
      "treatment_time": 18.0,
      "unit": "firm_01",
      "size": 0.07354417474748191,
      "leverage": 0.3516227027862885,
      "instrument_z": 1.0577328335812757,
      "endogenous_x": 0.2791971515539841,
      "outcome_y": 7.582391886802917,
      "binary_outcome": 0,
      "count_outcome": 3,
      "multiclass_outcome": 2,
      "secondary_outcome": 7.862834793778379,
      "running_score": 0.1041811916633471,
      "export_flow": 57.07600314125128,
      "origin_gdp": 6556.682201676948,
      "destination_gdp": 5232.980863080612,
      "distance_km": 507.1614318866007,
      "working_capital": 32363.71438557003,
      "retained_earnings": 20439.56234734776,
      "ebit": 16541.7141272288,
      "market_equity": 172178.88113898985,
      "sales": 188846.9724500364,
      "total_assets": 249886.2196283108,
      "total_liabilities": 107733.29948282472,
      "net_income": 11302.34191159805,
      "revenue": 188846.9724500364,
      "equity": 142152.92014548602
    },
    {
      "firm_id": "firm_01",
      "date": "2018-04-30",
      "calendar_year": 2018,
      "month_index": 4,
      "treated": 1,
      "post": 0,
      "staggered_post": 0,
      "event_time": -15,
      "staggered_event_time": -15.0,
      "treatment_time": 18.0,
      "unit": "firm_01",
      "size": 0.1383531483720637,
      "leverage": 0.4645773714523529,
      "instrument_z": 1.2478999752354007,
      "endogenous_x": 1.693126004491981,
      "outcome_y": 8.19643779930995,
      "binary_outcome": 0,
      "count_outcome": 1,
      "multiclass_outcome": 0,
      "secondary_outcome": 8.591393326330843,
      "running_score": -0.0371038537441296,
      "export_flow": 62.46581320633146,
      "origin_gdp": 6153.677585204073,
      "destination_gdp": 5173.463633447217,
      "distance_km": 513.0100149914846,
      "working_capital": 38743.845293878185,
      "retained_earnings": 25784.46384991348,
      "ebit": 20876.326013351547,
      "market_equity": 208936.74254947563,
      "sales": 240381.6312641816,
      "total_assets": 316001.4382922193,
      "total_liabilities": 139897.74841078912,
      "net_income": 12788.568799857552,
      "revenue": 240381.6312641816,
      "equity": 176103.68988143018
    },
    {
      "firm_id": "firm_01",
      "date": "2018-05-31",
      "calendar_year": 2018,
      "month_index": 5,
      "treated": 1,
      "post": 0,
      "staggered_post": 0,
      "event_time": -14,
      "staggered_event_time": -14.0,
      "treatment_time": 18.0,
      "unit": "firm_01",
      "size": 0.06443097245304427,
      "leverage": 0.34202038114414895,
      "instrument_z": -0.7576141862667286,
      "endogenous_x": -0.6336680485148168,
      "outcome_y": 6.775339604671813,
      "binary_outcome": 0,
      "count_outcome": 3,
      "multiclass_outcome": 1,
      "secondary_outcome": 6.579443540901458,
      "running_score": -0.288971942617631,
      "export_flow": 66.27852765987814,
      "origin_gdp": 6317.890930335069,
      "destination_gdp": 5393.903338564485,
      "distance_km": 492.4764703621588,
      "working_capital": 31111.809184562982,
      "retained_earnings": 19983.230564093214,
      "ebit": 16142.833031463188,
      "market_equity": 161540.15909079957,
      "sales": 184913.84896508945,
      "total_assets": 241772.51332008973,
      "total_liabilities": 105571.86947679768,
      "net_income": 16352.727029225927,
      "revenue": 184913.84896508945,
      "equity": 136200.64384329203
    },
    {
      "firm_id": "firm_01",
      "date": "2018-06-30",
      "calendar_year": 2018,
      "month_index": 6,
      "treated": 1,
      "post": 0,
      "staggered_post": 0,
      "event_time": -13,
      "staggered_event_time": -13.0,
      "treatment_time": 18.0,
      "unit": "firm_01",
      "size": 0.22779460490414552,
      "leverage": 0.17323311947184747,
      "instrument_z": 0.9993160670023692,
      "endogenous_x": -0.1402526508296088,
      "outcome_y": 7.332408657947028,
      "binary_outcome": 1,
      "count_outcome": 2,
      "multiclass_outcome": 1,
      "secondary_outcome": 7.2307023588412,
      "running_score": 1.610069527065623,
      "export_flow": 46.98808312387908,
      "origin_gdp": 6079.331742630903,
      "destination_gdp": 5564.469736773411,
      "distance_km": 516.7979022942117,
      "working_capital": 56846.90050534881,
      "retained_earnings": 36106.332343028254,
      "ebit": 29168.07265093644,
      "market_equity": 296217.28818743635,
      "sales": 321302.196893001,
      "total_assets": 436901.5219072232,
      "total_liabilities": 194827.7331239405,
      "net_income": 28293.973187214026,
      "revenue": 321302.196893001,
      "equity": 242073.7887832827
    },
    {
      "firm_id": "firm_01",
      "date": "2018-07-31",
      "calendar_year": 2018,
      "month_index": 7,
      "treated": 1,
      "post": 0,
      "staggered_post": 0,
      "event_time": -12,
      "staggered_event_time": -12.0,
      "treatment_time": 18.0,
      "unit": "firm_01",
      "size": 0.20054576208645528,
      "leverage": 0.49866759220211665,
      "instrument_z": 0.8494519105744235,
      "endogenous_x": 1.2847737900498406,
      "outcome_y": 9.385157683987362,
      "binary_outcome": 0,
      "count_outcome": 5,
      "multiclass_outcome": 1,
      "secondary_outcome": 9.442496052205518,
      "running_score": 1.565045718115602,
      "export_flow": 55.69756298015628,
      "origin_gdp": 6847.48656044833,
      "destination_gdp": 5313.3126876815,
      "distance_km": 503.1845860521783,
      "working_capital": 48257.00446747969,
      "retained_earnings": 32770.69255962545,
      "ebit": 26465.26712255711,
      "market_equity": 265363.41845645854,
      "sales": 290960.9783879348,
      "total_assets": 395840.464240584,
      "total_liabilities": 173827.29372892028,
      "net_income": 27036.3524134082,
      "revenue": 290960.9783879348,
      "equity": 222013.1705116637
    },
    {
      "firm_id": "firm_01",
      "date": "2018-08-31",
      "calendar_year": 2018,
      "month_index": 8,
      "treated": 1,
      "post": 0,
      "staggered_post": 0,
      "event_time": -11,
      "staggered_event_time": -11.0,
      "treatment_time": 18.0,
      "unit": "firm_01",
      "size": 0.09112188750881965,
      "leverage": 0.398124105507735,
      "instrument_z": -1.836891761801076,
      "endogenous_x": -1.1839305114729957,
      "outcome_y": 6.077208583694369,
      "binary_outcome": 1,
      "count_outcome": 3,
      "multiclass_outcome": 1,
      "secondary_outcome": 5.9464411345483175,
      "running_score": -0.0177468320860682,
      "export_flow": 68.34463620152061,
      "origin_gdp": 5994.80949019463,
      "destination_gdp": 5294.319947755545,
      "distance_km": 509.4082722198322,
      "working_capital": 34716.7539404328,
      "retained_earnings": 22045.02114661751,
      "ebit": 17803.667831022263,
      "market_equity": 176719.89675633676,
      "sales": 197118.2582333428,
      "total_assets": 266313.1771380505,
      "total_liabilities": 117957.3933566294,
      "net_income": 18256.826160179706,
      "revenue": 197118.2582333428,
      "equity": 148355.78378142117
    }
  ],
  "audit_trail": {
    "source_asset_id": "742a2af5-b7f8-4b12-8914-a535cd9ee440",
    "source_asset_title": "panel_dataset.csv",
    "prepared_asset_id": "7a79d0d2-3da8-4460-9c51-2f180f2828e7",
    "prepared_download_url": "/api/assets/7a79d0d2-3da8-4460-9c51-2f180f2828e7/download",
    "template_id": "",
    "template_name": "",
    "variant_label": "minmax_variant",
    "variant_spec": {
      "impute_method": "mean",
      "minmax_scale_columns": [
        "size",
        "leverage"
      ],
      "outlier_threshold": 1.25
    },
    "effective_specification": {
      "asset_id": "742a2af5-b7f8-4b12-8914-a535cd9ee440",
      "workflow_group": "cleaning_transforms",
      "impute_columns": [
        "size",
        "leverage"
      ],
      "winsorize_columns": [
        "outcome_y"
      ],
      "winsor_lower_quantile": 0.01,
      "winsor_upper_quantile": 0.99,
      "outlier_columns": [
        "outcome_y"
      ],
      "outlier_method": "iqr",
      "impute_method": "mean",
      "minmax_scale_columns": [
        "size",
        "leverage"
      ],
      "outlier_threshold": 1.25
    },
    "manual_checklist": [
      "Download the prepared asset and compare row/column counts with rows_after_prepare and columns.",
      "Reapply each cleaning step in order: imputation, winsorization, transforms, outlier filter, and missing-value filtering.",
      "Verify the preview_rows against the downloaded prepared sample."
    ],
    "operations": {
      "required_columns": [],
      "numeric_columns": [],
      "binary_columns": [],
      "date_columns": [],
      "imputed_columns": {
        "size": "mean",
        "leverage": "mean"
      },
      "winsorized_columns": {
        "outcome_y": {
          "lower": 0.01,
          "upper": 0.99
        }
      },
      "transformed_columns": {
        "log": [],
        "zscore": [],
        "minmax": [
          "size",
          "leverage"
        ]
      },
      "time_series_features": {
        "sort_column": "",
        "group_column": "",
        "difference_columns": [],
        "return_columns": [],
        "lag_columns": [],
        "lead_columns": [],
        "rolling_mean_columns": [],
        "rolling_volatility_columns": []
      },
      "derived_columns": [],
      "outlier_columns": [
        "outcome_y"
      ],
      "outlier_method": "iqr",
      "outlier_threshold": 1.25,
      "drop_duplicates": true,
      "drop_missing_required": true,
      "workflow_group": "cleaning_transforms"
    }
  },
  "result_detail_path": "/data-lab/results/processing/7a79d0d2-3da8-4460-9c51-2f180f2828e7",
  "profile": {
    "asset": {
      "id": "7a79d0d2-3da8-4460-9c51-2f180f2828e7",
      "kind": "dataset_csv",
      "title": "panel_dataset-prepared.csv",
      "filename": "panel_dataset-prepared.csv",
      "description": "Prepared analysis sample derived from panel_dataset.csv",
      "content_type": "text/csv",
      "source_url": "",
      "metadata": {
        "size_bytes": 287930,
        "original_filename": "panel_dataset-prepared.csv",
        "storage_backend": "local",
        "preparation_summary": {
          "rows_initial": 648,
          "rows_after_prepare": 648,
          "rows_removed_for_missing_required": 0,
          "duplicate_rows_removed": 0,
          "columns": [
            "firm_id",
            "date",
            "calendar_year",
            "month_index",
            "treated",
            "post",
            "staggered_post",
            "event_time",
            "staggered_event_time",
            "treatment_time",
            "unit",
            "size",
            "leverage",
            "instrument_z",
            "endogenous_x",
            "outcome_y",
            "binary_outcome",
            "count_outcome",
            "multiclass_outcome",
            "secondary_outcome",
            "running_score",
            "export_flow",
            "origin_gdp",
            "destination_gdp",
            "distance_km",
            "working_capital",
            "retained_earnings",
            "ebit",
            "market_equity",
            "sales",
            "total_assets",
            "total_liabilities",
            "net_income",
            "revenue",
            "equity"
          ],
          "required_columns": [],
          "numeric_columns": [],
          "binary_columns": [],
          "date_columns": [],
          "imputed_columns": {
            "size": "mean",
            "leverage": "mean"
          },
          "winsorized_columns": {
            "outcome_y": {
              "lower": 0.01,
              "upper": 0.99
            }
          },
          "transformed_columns": {
            "log": [],
            "zscore": [],
            "minmax": [
              "size",
              "leverage"
            ]
          },
          "time_series_features": {
            "sort_column": "",
            "group_column": "",
            "difference_columns": [],
            "return_columns": [],
            "lag_columns": [],
            "lead_columns": [],
            "rolling_mean_columns": [],
            "rolling_volatility_columns": []
          },
          "derived_columns": [],
          "outlier_columns": [
            "outcome_y"
          ],
          "outlier_method": "iqr",
          "outlier_threshold": 1.25,
          "outliers_removed": 0,
          "missing_by_column": {
            "firm_id": 0,
            "date": 0,
            "calendar_year": 0,
            "month_index": 0,
            "treated": 0,
            "post": 0,
            "staggered_post": 0,
            "event_time": 0,
            "staggered_event_time": 324,
            "treatment_time": 324,
            "unit": 0,
            "size": 0,
            "leverage": 0,
            "instrument_z": 0,
            "endogenous_x": 0,
            "outcome_y": 0,
            "binary_outcome": 0,
            "count_outcome": 0,
            "multiclass_outcome": 0,
            "secondary_outcome": 0,
            "running_score": 0,
            "export_flow": 0,
            "origin_gdp": 0,
            "destination_gdp": 0,
            "distance_km": 0,
            "working_capital": 0,
            "retained_earnings": 0,
            "ebit": 0,
            "market_equity": 0,
            "sales": 0,
            "total_assets": 0,
            "total_liabilities": 0,
            "net_income": 0,
            "revenue": 0,
            "equity": 0
          }
        },
        "source_asset_id": "742a2af5-b7f8-4b12-8914-a535cd9ee440"
      },
      "created_at": "2026-04-02T03:16:15.548557",
      "updated_at": "2026-04-02T03:16:15.558016"
    },
    "rows": 648,
    "columns": 35,
    "duplicate_rows_detected": 0,
    "column_profiles": [
      {
        "name": "firm_id",
        "source_name": "firm_id",
        "role": "categorical",
        "dtype": "object",
        "missing_count": 0,
        "non_null_count": 648,
        "unique_count": 18,
        "sample_values": [
          "firm_01",
          "firm_01",
          "firm_01",
          "firm_01"
        ]
      },
      {
        "name": "date",
        "source_name": "date",
        "role": "date",
        "dtype": "object",
        "missing_count": 0,
        "non_null_count": 648,
        "unique_count": 36,
        "sample_values": [
          "2018-01-31",
          "2018-02-28",
          "2018-03-31",
          "2018-04-30"
        ],
        "min": "2018-01-31T00:00:00",
        "max": "2020-12-31T00:00:00"
      },
      {
        "name": "calendar_year",
        "source_name": "calendar_year",
        "role": "numeric",
        "dtype": "int64",
        "missing_count": 0,
        "non_null_count": 648,
        "unique_count": 3,
        "sample_values": [
          2018,
          2018,
          2018,
          2018
        ],
        "mean": 2019.0,
        "std": 0.8171273238421276,
        "min": 2018.0,
        "max": 2020.0
      },
      {
        "name": "month_index",
        "source_name": "month_index",
        "role": "numeric",
        "dtype": "int64",
        "missing_count": 0,
        "non_null_count": 648,
        "unique_count": 36,
        "sample_values": [
          1,
          2,
          3,
          4
        ],
        "mean": 18.5,
        "std": 10.396319643648956,
        "min": 1.0,
        "max": 36.0
      },
      {
        "name": "treated",
        "source_name": "treated",
        "role": "binary",
        "dtype": "int64",
        "missing_count": 0,
        "non_null_count": 648,
        "unique_count": 2,
        "sample_values": [
          1,
          1,
          1,
          1
        ],
        "mean": 0.5,
        "std": 0.5003862495747899,
        "min": 0.0,
        "max": 1.0
      },
      {
        "name": "post",
        "source_name": "post",
        "role": "binary",
        "dtype": "int64",
        "missing_count": 0,
        "non_null_count": 648,
        "unique_count": 2,
        "sample_values": [
          0,
          0,
          0,
          0
        ],
        "mean": 0.5,
        "std": 0.5003862495747899,
        "min": 0.0,
        "max": 1.0
      },
      {
        "name": "staggered_post",
        "source_name": "staggered_post",
        "role": "binary",
        "dtype": "int64",
        "missing_count": 0,
        "non_null_count": 648,
        "unique_count": 2,
        "sample_values": [
          0,
          0,
          0,
          0
        ],
        "mean": 0.23148148148148148,
        "std": 0.4221051565433561,
        "min": 0.0,
        "max": 1.0
      },
      {
        "name": "event_time",
        "source_name": "event_time",
        "role": "numeric",
        "dtype": "int64",
        "missing_count": 0,
        "non_null_count": 648,
        "unique_count": 36,
        "sample_values": [
          -18,
          -17,
          -16,
          -15
        ],
        "mean": -0.5,
        "std": 10.396319643648956,
        "min": -18.0,
        "max": 17.0
      },
      {
        "name": "staggered_event_time",
        "source_name": "staggered_event_time",
        "role": "numeric",
        "dtype": "object",
        "missing_count": 324,
        "non_null_count": 324,
        "unique_count": 39,
        "sample_values": [
          -18.0,
          -17.0,
          -16.0,
          -15.0
        ],
        "mean": -1.8333333333333333,
        "std": 10.468439964680394,
        "min": -21.0,
        "max": 17.0
      },
      {
        "name": "treatment_time",
        "source_name": "treatment_time",
        "role": "numeric",
        "dtype": "object",
        "missing_count": 324,
        "non_null_count": 324,
        "unique_count": 4,
        "sample_values": [
          18.0,
          18.0,
          18.0,
          18.0
        ],
        "mean": 19.333333333333332,
        "std": 1.1564866191658238,
        "min": 18.0,
        "max": 21.0
      },
      {
        "name": "unit",
        "source_name": "unit",
        "role": "categorical",
        "dtype": "object",
        "missing_count": 0,
        "non_null_count": 648,
        "unique_count": 18,
        "sample_values": [
          "firm_01",
          "firm_01",
          "firm_01",
          "firm_01"
        ]
      },
      {
        "name": "size",
        "source_name": "size",
        "role": "numeric",
        "dtype": "float64",
        "missing_count": 0,
        "non_null_count": 648,
        "unique_count": 648,
        "sample_values": [
          0.2657518825675091,
          0.0,
          0.0735441747474819,
          0.1383531483720637
        ],
        "mean": 0.5469218981678196,
        "std": 0.20840244801578925,
        "min": 0.0,
        "max": 1.0
      },
      {
        "name": "leverage",
        "source_name": "leverage",
        "role": "numeric",
        "dtype": "float64",
        "missing_count": 0,
        "non_null_count": 648,
        "unique_count": 648,
        "sample_values": [
          0.4629056287983223,
          0.3682188743444447,
          0.3516227027862885,
          0.4645773714523529
        ],
        "mean": 0.5234635319881041,
        "std": 0.1567973828923209,
        "min": 0.0,
        "max": 1.0
      },
      {
        "name": "instrument_z",
        "source_name": "instrument_z",
        "role": "numeric",
        "dtype": "float64",
        "missing_count": 0,
        "non_null_count": 648,
        "unique_count": 648,
        "sample_values": [
          -0.1435168424451554,
          1.4316570462193818,
          1.0577328335812757,
          1.2478999752354007
        ],
        "mean": 0.06666376307133817,
        "std": 0.9398622849749344,
        "min": -2.854993584461037,
        "max": 2.8985894914913684
      },
      {
        "name": "endogenous_x",
        "source_name": "endogenous_x",
        "role": "numeric",
        "dtype": "float64",
        "missing_count": 0,
        "non_null_count": 648,
        "unique_count": 648,
        "sample_values": [
          0.2785972991161518,
          1.1977342200420291,
          0.2791971515539841,
          1.693126004491981
        ],
        "mean": 0.04773874603334642,
        "std": 0.7905014192560844,
        "min": -2.7851612520887707,
        "max": 2.712189695300858
      },
      {
        "name": "outcome_y",
        "source_name": "outcome_y",
        "role": "numeric",
        "dtype": "float64",
        "missing_count": 0,
        "non_null_count": 648,
        "unique_count": 636,
        "sample_values": [
          8.281342947667275,
          7.161166663415577,
          7.582391886802917,
          8.19643779930995
        ],
        "mean": 9.81726279080171,
        "std": 1.7854073538884956,
        "min": 6.010286272583683,
        "max": 13.700494126499567
      },
      {
        "name": "binary_outcome",
        "source_name": "binary_outcome",
        "role": "binary",
        "dtype": "int64",
        "missing_count": 0,
        "non_null_count": 648,
        "unique_count": 2,
        "sample_values": [
          0,
          1,
          0,
          0
        ],
        "mean": 0.48148148148148145,
        "std": 0.500042931352846,
        "min": 0.0,
        "max": 1.0
      },
      {
        "name": "count_outcome",
        "source_name": "count_outcome",
        "role": "numeric",
        "dtype": "int64",
        "missing_count": 0,
        "non_null_count": 648,
        "unique_count": 15,
        "sample_values": [
          1,
          3,
          3,
          1
        ],
        "mean": 4.320987654320987,
        "std": 2.4967473641032383,
        "min": 0.0,
        "max": 15.0
      },
      {
        "name": "multiclass_outcome",
        "source_name": "multiclass_outcome",
        "role": "numeric",
        "dtype": "int64",
        "missing_count": 0,
        "non_null_count": 648,
        "unique_count": 3,
        "sample_values": [
          0,
          1,
          2,
          0
        ],
        "mean": 1.0771604938271604,
        "std": 0.6696581232409793,
        "min": 0.0,
        "max": 2.0
      },
      {
        "name": "secondary_outcome",
        "source_name": "secondary_outcome",
        "role": "numeric",
        "dtype": "float64",
        "missing_count": 0,
        "non_null_count": 648,
        "unique_count": 648,
        "sample_values": [
          8.061791269331776,
          7.318611368946235,
          7.862834793778379,
          8.591393326330843
        ],
        "mean": 9.855688102697247,
        "std": 1.8106375555056882,
        "min": 5.306578534706126,
        "max": 14.50454764052591
      },
      {
        "name": "running_score",
        "source_name": "running_score",
        "role": "numeric",
        "dtype": "float64",
        "missing_count": 0,
        "non_null_count": 648,
        "unique_count": 648,
        "sample_values": [
          0.7698387038457276,
          -1.2578541177844715,
          0.1041811916633471,
          -0.0371038537441296
        ],
        "mean": 0.06268341743046511,
        "std": 0.8603784971016748,
        "min": -1.4916783418634405,
        "max": 1.6472069362780783
      },
      {
        "name": "export_flow",
        "source_name": "export_flow",
        "role": "numeric",
        "dtype": "float64",
        "missing_count": 0,
        "non_null_count": 648,
        "unique_count": 648,
        "sample_values": [
          49.40883917797032,
          91.97699374857942,
          57.07600314125128,
          62.46581320633146
        ],
        "mean": 88.42262962142519,
        "std": 22.819950976112032,
        "min": 42.1100834373322,
        "max": 176.48105313708592
      },
      {
        "name": "origin_gdp",
        "source_name": "origin_gdp",
        "role": "numeric",
        "dtype": "float64",
        "missing_count": 0,
        "non_null_count": 648,
        "unique_count": 648,
        "sample_values": [
          6707.077236995387,
          6549.205151959514,
          6556.682201676948,
          6153.677585204073
        ],
        "mean": 8320.058626382031,
        "std": 1169.790515756106,
        "min": 5904.601127127199,
        "max": 11850.459789846487
      },
      {
        "name": "destination_gdp",
        "source_name": "destination_gdp",
        "role": "numeric",
        "dtype": "float64",
        "missing_count": 0,
        "non_null_count": 648,
        "unique_count": 648,
        "sample_values": [
          5124.128155689759,
          4695.745866446325,
          5232.980863080612,
          5173.463633447217
        ],
        "mean": 6481.18940155939,
        "std": 1050.0523633803878,
        "min": 4298.142781907615,
        "max": 8943.665767474742
      },
      {
        "name": "distance_km",
        "source_name": "distance_km",
        "role": "numeric",
        "dtype": "float64",
        "missing_count": 0,
        "non_null_count": 648,
        "unique_count": 648,
        "sample_values": [
          506.1984144232085,
          499.9748647163789,
          507.1614318866007,
          513.0100149914846
        ],
        "mean": 534.1432200027671,
        "std": 43.798271225939295,
        "min": 392.0234674116797,
        "max": 671.0039990745307
      },
      {
        "name": "working_capital",
        "source_name": "working_capital",
        "role": "numeric",
        "dtype": "float64",
        "missing_count": 0,
        "non_null_count": 648,
        "unique_count": 648,
        "sample_values": [
          61057.22892506472,
          25865.74300359386,
          32363.71438557003,
          38743.845293878185
        ],
        "mean": 238536.4360659576,
        "std": 184513.0786722772,
        "min": 25865.74300359386,
        "max": 982448.7529440526
      },
      {
        "name": "retained_earnings",
        "source_name": "retained_earnings",
        "role": "numeric",
        "dtype": "float64",
        "missing_count": 0,
        "non_null_count": 648,
        "unique_count": 648,
        "sample_values": [
          41137.34917451515,
          15937.67861929455,
          20439.56234734776,
          25784.46384991348
        ],
        "mean": 150723.59558666375,
        "std": 115914.90937656877,
        "min": 15937.67861929455,
        "max": 590521.6056183792
      },
      {
        "name": "ebit",
        "source_name": "ebit",
        "role": "numeric",
        "dtype": "float64",
        "missing_count": 0,
        "non_null_count": 648,
        "unique_count": 648,
        "sample_values": [
          33273.31812219427,
          12858.699383533743,
          16541.7141272288,
          20876.326013351547
        ],
        "mean": 121812.14668010933,
        "std": 93668.8552795061,
        "min": 12858.699383533743,
        "max": 477248.3157204556
      },
      {
        "name": "market_equity",
        "source_name": "market_equity",
        "role": "numeric",
        "dtype": "float64",
        "missing_count": 0,
        "non_null_count": 648,
        "unique_count": 648,
        "sample_values": [
          335260.0152858213,
          124948.65584723122,
          172178.88113898985,
          208936.74254947563
        ],
        "mean": 1237390.874814948,
        "std": 953048.2564370641,
        "min": 124948.65584723122,
        "max": 4901599.773576712
      },
      {
        "name": "sales",
        "source_name": "sales",
        "role": "numeric",
        "dtype": "float64",
        "missing_count": 0,
        "non_null_count": 648,
        "unique_count": 648,
        "sample_values": [
          383648.0257341592,
          143429.89314427826,
          188846.9724500364,
          240381.6312641816
        ],
        "mean": 1362487.3408581177,
        "std": 1046737.0880231429,
        "min": 143429.89314427826,
        "max": 5336828.230860783
      },
      {
        "name": "total_assets",
        "source_name": "total_assets",
        "role": "numeric",
        "dtype": "float64",
        "missing_count": 0,
        "non_null_count": 648,
        "unique_count": 648,
        "sample_values": [
          501293.02907292894,
          191449.74034320377,
          249886.2196283108,
          316001.4382922193
        ],
        "mean": 1828264.2533428727,
        "std": 1405099.949992699,
        "min": 191449.74034320377,
        "max": 7162906.740703089
      },
      {
        "name": "total_liabilities",
        "source_name": "total_liabilities",
        "role": "numeric",
        "dtype": "float64",
        "missing_count": 0,
        "non_null_count": 648,
        "unique_count": 648,
        "sample_values": [
          213372.0724041828,
          84857.58709080162,
          107733.29948282472,
          139897.74841078912
        ],
        "mean": 794695.3457095094,
        "std": 610063.847876903,
        "min": 84857.58709080162,
        "max": 3075675.867147615
      },
      {
        "name": "net_income",
        "source_name": "net_income",
        "role": "numeric",
        "dtype": "float64",
        "missing_count": 0,
        "non_null_count": 648,
        "unique_count": 648,
        "sample_values": [
          26375.54605689663,
          15525.445856681252,
          11302.34191159805,
          12788.568799857552
        ],
        "mean": 110881.94135957905,
        "std": 91105.04410448446,
        "min": 11302.34191159805,
        "max": 575316.5998152838
      },
      {
        "name": "revenue",
        "source_name": "revenue",
        "role": "numeric",
        "dtype": "float64",
        "missing_count": 0,
        "non_null_count": 648,
        "unique_count": 648,
        "sample_values": [
          383648.0257341592,
          143429.89314427826,
          188846.9724500364,
          240381.6312641816
        ],
        "mean": 1362487.3408581177,
        "std": 1046737.0880231429,
        "min": 143429.89314427826,
        "max": 5336828.230860783
      },
      {
        "name": "equity",
        "source_name": "equity",
        "role": "numeric",
        "dtype": "float64",
        "missing_count": 0,
        "non_null_count": 648,
        "unique_count": 648,
        "sample_values": [
          287920.9566687462,
          106592.15325240216,
          142152.92014548602,
          176103.68988143018
        ],
        "mean": 1033568.9076333635,
        "std": 795605.3712297033,
        "min": 106592.15325240216,
        "max": 4087230.873555474
      }
    ],
    "column_roles": {
      "numeric": [
        "calendar_year",
        "month_index",
        "event_time",
        "staggered_event_time",
        "treatment_time",
        "size",
        "leverage",
        "instrument_z",
        "endogenous_x",
        "outcome_y",
        "count_outcome",
        "multiclass_outcome",
        "secondary_outcome",
        "running_score",
        "export_flow",
        "origin_gdp",
        "destination_gdp",
        "distance_km",
        "working_capital",
        "retained_earnings",
        "ebit",
        "market_equity",
        "sales",
        "total_assets",
        "total_liabilities",
        "net_income",
        "revenue",
        "equity"
      ],
      "binary": [
        "treated",
        "post",
        "staggered_post",
        "binary_outcome"
      ],
      "date": [
        "date"
      ],
      "categorical": [
        "firm_id",
        "unit"
      ],
      "text": [],
      "empty": []
    },
    "preview_rows": [
      {
        "firm_id": "firm_01",
        "date": "2018-01-31",
        "calendar_year": 2018,
        "month_index": 1,
        "treated": 1,
        "post": 0,
        "staggered_post": 0,
        "event_time": -18,
        "staggered_event_time": -18.0,
        "treatment_time": 18.0,
        "unit": "firm_01",
        "size": 0.2657518825675091,
        "leverage": 0.4629056287983223,
        "instrument_z": -0.1435168424451554,
        "endogenous_x": 0.2785972991161518,
        "outcome_y": 8.281342947667275,
        "binary_outcome": 0,
        "count_outcome": 1,
        "multiclass_outcome": 0,
        "secondary_outcome": 8.061791269331776,
        "running_score": 0.7698387038457276,
        "export_flow": 49.40883917797032,
        "origin_gdp": 6707.077236995387,
        "destination_gdp": 5124.128155689759,
        "distance_km": 506.1984144232085,
        "working_capital": 61057.22892506472,
        "retained_earnings": 41137.34917451515,
        "ebit": 33273.31812219427,
        "market_equity": 335260.0152858213,
        "sales": 383648.0257341592,
        "total_assets": 501293.02907292894,
        "total_liabilities": 213372.0724041828,
        "net_income": 26375.54605689663,
        "revenue": 383648.0257341592,
        "equity": 287920.9566687462
      },
      {
        "firm_id": "firm_01",
        "date": "2018-02-28",
        "calendar_year": 2018,
        "month_index": 2,
        "treated": 1,
        "post": 0,
        "staggered_post": 0,
        "event_time": -17,
        "staggered_event_time": -17.0,
        "treatment_time": 18.0,
        "unit": "firm_01",
        "size": 0.0,
        "leverage": 0.3682188743444447,
        "instrument_z": 1.4316570462193818,
        "endogenous_x": 1.1977342200420291,
        "outcome_y": 7.161166663415577,
        "binary_outcome": 1,
        "count_outcome": 3,
        "multiclass_outcome": 1,
        "secondary_outcome": 7.318611368946235,
        "running_score": -1.2578541177844715,
        "export_flow": 91.97699374857942,
        "origin_gdp": 6549.205151959514,
        "destination_gdp": 4695.745866446325,
        "distance_km": 499.9748647163789,
        "working_capital": 25865.74300359386,
        "retained_earnings": 15937.67861929455,
        "ebit": 12858.699383533743,
        "market_equity": 124948.65584723122,
        "sales": 143429.89314427826,
        "total_assets": 191449.74034320377,
        "total_liabilities": 84857.58709080162,
        "net_income": 15525.445856681252,
        "revenue": 143429.89314427826,
        "equity": 106592.15325240216
      },
      {
        "firm_id": "firm_01",
        "date": "2018-03-31",
        "calendar_year": 2018,
        "month_index": 3,
        "treated": 1,
        "post": 0,
        "staggered_post": 0,
        "event_time": -16,
        "staggered_event_time": -16.0,
        "treatment_time": 18.0,
        "unit": "firm_01",
        "size": 0.0735441747474819,
        "leverage": 0.3516227027862885,
        "instrument_z": 1.0577328335812757,
        "endogenous_x": 0.2791971515539841,
        "outcome_y": 7.582391886802917,
        "binary_outcome": 0,
        "count_outcome": 3,
        "multiclass_outcome": 2,
        "secondary_outcome": 7.862834793778379,
        "running_score": 0.1041811916633471,
        "export_flow": 57.07600314125128,
        "origin_gdp": 6556.682201676948,
        "destination_gdp": 5232.980863080612,
        "distance_km": 507.1614318866007,
        "working_capital": 32363.71438557003,
        "retained_earnings": 20439.56234734776,
        "ebit": 16541.7141272288,
        "market_equity": 172178.88113898985,
        "sales": 188846.9724500364,
        "total_assets": 249886.2196283108,
        "total_liabilities": 107733.29948282472,
        "net_income": 11302.34191159805,
        "revenue": 188846.9724500364,
        "equity": 142152.92014548602
      },
      {
        "firm_id": "firm_01",
        "date": "2018-04-30",
        "calendar_year": 2018,
        "month_index": 4,
        "treated": 1,
        "post": 0,
        "staggered_post": 0,
        "event_time": -15,
        "staggered_event_time": -15.0,
        "treatment_time": 18.0,
        "unit": "firm_01",
        "size": 0.1383531483720637,
        "leverage": 0.4645773714523529,
        "instrument_z": 1.2478999752354007,
        "endogenous_x": 1.693126004491981,
        "outcome_y": 8.19643779930995,
        "binary_outcome": 0,
        "count_outcome": 1,
        "multiclass_outcome": 0,
        "secondary_outcome": 8.591393326330843,
        "running_score": -0.0371038537441296,
        "export_flow": 62.46581320633146,
        "origin_gdp": 6153.677585204073,
        "destination_gdp": 5173.463633447217,
        "distance_km": 513.0100149914846,
        "working_capital": 38743.845293878185,
        "retained_earnings": 25784.46384991348,
        "ebit": 20876.326013351547,
        "market_equity": 208936.74254947563,
        "sales": 240381.6312641816,
        "total_assets": 316001.4382922193,
        "total_liabilities": 139897.74841078912,
        "net_income": 12788.568799857552,
        "revenue": 240381.6312641816,
        "equity": 176103.68988143018
      },
      {
        "firm_id": "firm_01",
        "date": "2018-05-31",
        "calendar_year": 2018,
        "month_index": 5,
        "treated": 1,
        "post": 0,
        "staggered_post": 0,
        "event_time": -14,
        "staggered_event_time": -14.0,
        "treatment_time": 18.0,
        "unit": "firm_01",
        "size": 0.0644309724530442,
        "leverage": 0.3420203811441489,
        "instrument_z": -0.7576141862667286,
        "endogenous_x": -0.6336680485148168,
        "outcome_y": 6.775339604671813,
        "binary_outcome": 0,
        "count_outcome": 3,
        "multiclass_outcome": 1,
        "secondary_outcome": 6.579443540901458,
        "running_score": -0.288971942617631,
        "export_flow": 66.27852765987814,
        "origin_gdp": 6317.890930335069,
        "destination_gdp": 5393.903338564485,
        "distance_km": 492.4764703621588,
        "working_capital": 31111.809184562982,
        "retained_earnings": 19983.230564093214,
        "ebit": 16142.833031463188,
        "market_equity": 161540.15909079957,
        "sales": 184913.84896508945,
        "total_assets": 241772.51332008973,
        "total_liabilities": 105571.86947679768,
        "net_income": 16352.727029225927,
        "revenue": 184913.84896508945,
        "equity": 136200.64384329203
      },
      {
        "firm_id": "firm_01",
        "date": "2018-06-30",
        "calendar_year": 2018,
        "month_index": 6,
        "treated": 1,
        "post": 0,
        "staggered_post": 0,
        "event_time": -13,
        "staggered_event_time": -13.0,
        "treatment_time": 18.0,
        "unit": "firm_01",
        "size": 0.2277946049041455,
        "leverage": 0.1732331194718474,
        "instrument_z": 0.9993160670023692,
        "endogenous_x": -0.1402526508296088,
        "outcome_y": 7.332408657947028,
        "binary_outcome": 1,
        "count_outcome": 2,
        "multiclass_outcome": 1,
        "secondary_outcome": 7.2307023588412,
        "running_score": 1.610069527065623,
        "export_flow": 46.98808312387908,
        "origin_gdp": 6079.331742630903,
        "destination_gdp": 5564.469736773411,
        "distance_km": 516.7979022942117,
        "working_capital": 56846.90050534881,
        "retained_earnings": 36106.332343028254,
        "ebit": 29168.07265093644,
        "market_equity": 296217.28818743635,
        "sales": 321302.196893001,
        "total_assets": 436901.5219072232,
        "total_liabilities": 194827.7331239405,
        "net_income": 28293.973187214026,
        "revenue": 321302.196893001,
        "equity": 242073.7887832827
      },
      {
        "firm_id": "firm_01",
        "date": "2018-07-31",
        "calendar_year": 2018,
        "month_index": 7,
        "treated": 1,
        "post": 0,
        "staggered_post": 0,
        "event_time": -12,
        "staggered_event_time": -12.0,
        "treatment_time": 18.0,
        "unit": "firm_01",
        "size": 0.2005457620864552,
        "leverage": 0.4986675922021166,
        "instrument_z": 0.8494519105744235,
        "endogenous_x": 1.2847737900498406,
        "outcome_y": 9.385157683987362,
        "binary_outcome": 0,
        "count_outcome": 5,
        "multiclass_outcome": 1,
        "secondary_outcome": 9.442496052205518,
        "running_score": 1.565045718115602,
        "export_flow": 55.69756298015628,
        "origin_gdp": 6847.48656044833,
        "destination_gdp": 5313.3126876815,
        "distance_km": 503.1845860521783,
        "working_capital": 48257.00446747969,
        "retained_earnings": 32770.69255962545,
        "ebit": 26465.26712255711,
        "market_equity": 265363.41845645854,
        "sales": 290960.9783879348,
        "total_assets": 395840.464240584,
        "total_liabilities": 173827.29372892028,
        "net_income": 27036.3524134082,
        "revenue": 290960.9783879348,
        "equity": 222013.1705116637
      },
      {
        "firm_id": "firm_01",
        "date": "2018-08-31",
        "calendar_year": 2018,
        "month_index": 8,
        "treated": 1,
        "post": 0,
        "staggered_post": 0,
        "event_time": -11,
        "staggered_event_time": -11.0,
        "treatment_time": 18.0,
        "unit": "firm_01",
        "size": 0.0911218875088196,
        "leverage": 0.398124105507735,
        "instrument_z": -1.836891761801076,
        "endogenous_x": -1.1839305114729957,
        "outcome_y": 6.077208583694369,
        "binary_outcome": 1,
        "count_outcome": 3,
        "multiclass_outcome": 1,
        "secondary_outcome": 5.9464411345483175,
        "running_score": -0.0177468320860682,
        "export_flow": 68.34463620152061,
        "origin_gdp": 5994.80949019463,
        "destination_gdp": 5294.319947755545,
        "distance_km": 509.4082722198322,
        "working_capital": 34716.7539404328,
        "retained_earnings": 22045.02114661751,
        "ebit": 17803.667831022263,
        "market_equity": 176719.89675633676,
        "sales": 197118.2582333428,
        "total_assets": 266313.1771380505,
        "total_liabilities": 117957.3933566294,
        "net_income": 18256.826160179706,
        "revenue": 197118.2582333428,
        "equity": 148355.78378142117
      }
    ],
    "suggested_models": [
      "ols",
      "logit",
      "probit",
      "ppml",
      "rdd",
      "historical_var",
      "parametric_var",
      "ewma_volatility",
      "capm",
      "mean_variance",
      "minimum_variance",
      "risk_parity",
      "did",
      "event_study",
      "fixed_effects",
      "arima",
      "var",
      "taylor_rule",
      "gravity",
      "iv_2sls",
      "panel_iv",
      "fama_french_3",
      "black_scholes",
      "binomial_option",
      "altman_z",
      "dupont",
      "rbc_dsge"
    ],
    "source_columns": {
      "firm_id": "firm_id",
      "date": "date",
      "calendar_year": "calendar_year",
      "month_index": "month_index",
      "treated": "treated",
      "post": "post",
      "staggered_post": "staggered_post",
      "event_time": "event_time",
      "staggered_event_time": "staggered_event_time",
      "treatment_time": "treatment_time",
      "unit": "unit",
      "size": "size",
      "leverage": "leverage",
      "instrument_z": "instrument_z",
      "endogenous_x": "endogenous_x",
      "outcome_y": "outcome_y",
      "binary_outcome": "binary_outcome",
      "count_outcome": "count_outcome",
      "multiclass_outcome": "multiclass_outcome",
      "secondary_outcome": "secondary_outcome",
      "running_score": "running_score",
      "export_flow": "export_flow",
      "origin_gdp": "origin_gdp",
      "destination_gdp": "destination_gdp",
      "distance_km": "distance_km",
      "working_capital": "working_capital",
      "retained_earnings": "retained_earnings",
      "ebit": "ebit",
      "market_equity": "market_equity",
      "sales": "sales",
      "total_assets": "total_assets",
      "total_liabilities": "total_liabilities",
      "net_income": "net_income",
      "revenue": "revenue",
      "equity": "equity"
    }
  },
  "interpretation": {
    "headline": "Cleaning Transforms created a reproducible prepared sample with full audit metadata.",
    "sections": [
      {
        "title": "What this processing run produced",
        "items": [
          "Prepared rows: 648.",
          "Missing-value drops: 0.",
          "Derived columns created: none."
        ]
      },
      {
        "title": "What a normal appendix should show",
        "items": [
          "A concise data-preparation log that lists the exact transformations applied in order.",
          "A preview or schema of the final prepared sample.",
          "A downloadable prepared dataset used for estimation."
        ]
      },
      {
        "title": "Manual replication focus",
        "items": [
          "Reapply imputation, winsorization, transforms, feature construction, and filtering in the documented order.",
          "Verify row and column counts against the saved preparation summary.",
          "Check transformation groups explicitly: {\"log\": [], \"zscore\": [], \"minmax\": [\"size\", \"leverage\"]}."
        ]
      }
    ],
    "paper_outputs": [
      "Preparation summary",
      "Prepared sample preview",
      "Downloadable prepared dataset"
    ]
  },
  "workspace_id": "4cd84637-1a2b-4173-a188-0d68ec5784a4"
}